franka_sim/__init__.py
franka_sim/franka_genesis_sim.py
franka_sim/franka_protocol.py
franka_sim/franka_sim_server.py
franka_sim/robot_state.py
franka_sim/run_server.py
franka_sim-0.1.13.dist-info/licenses/LICENSE
franka_sim-0.1.13.dist-info/METADATA
franka_sim-0.1.13.dist-info/WHEEL
franka_sim-0.1.13.dist-info/entry_points.txt
franka_sim-0.1.13.dist-info/top_level.txt
franka_sim-0.1.13.dist-info/RECORD
