Metadata-Version: 2.4
Name: franka-sim
Version: 0.1.13
Summary: A high-fidelity simulation server that implements the Franka robot network protocol, enabling seamless switching between simulation and hardware.
Author-email: Baris Yazici <barisyazici@alumni.sabanciuniv.edu>
License: Apache-2.0
Project-URL: Homepage, https://github.com/BarisYazici/libfranka-sim
Project-URL: Bug Tracker, https://github.com/BarisYazici/libfranka-sim/issues
Project-URL: Documentation, https://github.com/BarisYazici/libfranka-sim#readme
Keywords: robotics,simulation,franka,robot,genesis
Classifier: Development Status :: 4 - Beta
Classifier: Programming Language :: Python :: 3
Classifier: Programming Language :: Python :: 3.9
Classifier: Programming Language :: Python :: 3.10
Classifier: Programming Language :: Python :: 3.11
Classifier: License :: OSI Approved :: Apache Software License
Classifier: Topic :: Scientific/Engineering
Classifier: Topic :: Scientific/Engineering :: Artificial Intelligence
Classifier: Topic :: Scientific/Engineering :: Physics
Requires-Python: >=3.8
License-File: LICENSE
Requires-Dist: numpy==1.26.4
Requires-Dist: genesis-world==0.2.1
Requires-Dist: numba==0.60.0
Requires-Dist: torch>=2.0.0
Requires-Dist: pytest
Provides-Extra: dev
Requires-Dist: pre-commit>=3.5.0; extra == "dev"
Requires-Dist: black>=24.1.1; extra == "dev"
Requires-Dist: isort>=5.13.2; extra == "dev"
Requires-Dist: flake8>=7.0.0; extra == "dev"
Requires-Dist: flake8-docstrings>=1.7.0; extra == "dev"
Requires-Dist: pytest>=8.0.0; extra == "dev"
Requires-Dist: pytest-cov>=4.1.0; extra == "dev"
Dynamic: license-file
